{
  "flakes": [
    {
      "from": {
        "id": "emacs-builtins",
        "type": "indirect"
      },
      "to": {
        "lastModified": 1779147734,
        "narHash": "sha256-8Tupa1CVVPix9b5JjsvyflMLFFmQSZBj+y4H/JAiyvg=",
        "owner": "emacs-twist",
        "repo": "emacs-builtins",
        "rev": "b9d3aa84b0e4cc027feea2c05c52adce1f7c85dc",
        "type": "github"
      }
    },
    {
      "from": {
        "id": "emacs-overlay",
        "type": "indirect"
      },
      "to": {
        "lastModified": 1779389208,
        "narHash": "sha256-nTvPl9e2jnBNsiuQ0I5wq1VOpvVQcJuIynLMssO0LtQ=",
        "owner": "nix-community",
        "repo": "emacs-overlay",
        "rev": "c0ee65d473ebdd79e27ae32636054ea89ec990a8",
        "type": "github"
      }
    },
    {
      "from": {
        "id": "flake-compat",
        "type": "indirect"
      },
      "to": {
        "lastModified": 1767039857,
        "narHash": "sha256-vNpUSpF5Nuw8xvDLj2KCwwksIbjua2LZCqhV1LNRDns=",
        "owner": "edolstra",
        "repo": "flake-compat",
        "rev": "5edf11c44bc78a0d334f6334cdaf7d60d732daab",
        "type": "github"
      }
    },
    {
      "from": {
        "id": "flake-parts",
        "type": "indirect"
      },
      "to": {
        "lastModified": 1778716662,
        "narHash": "sha256-m1Yf0wZ8j1OHjTc2UwHwyQRSnNeSgLJOd7q5Y45hzi4=",
        "owner": "hercules-ci",
        "repo": "flake-parts",
        "rev": "f7c1a2d347e4c52d5fb8d10cb4d94b5884e546fb",
        "type": "github"
      }
    },
    {
      "from": {
        "id": "flake-utils",
        "type": "indirect"
      },
      "to": {
        "lastModified": 1731533236,
        "narHash": "sha256-l0KFg5HjrsfsO/JpG+r7fRrqm12kzFHyUHqHCVpMMbI=",
        "owner": "numtide",
        "repo": "flake-utils",
        "rev": "11707dc2f618dd54ca8739b309ec4fc024de578b",
        "type": "github"
      }
    },
    {
      "from": {
        "id": "home-manager-unstable",
        "type": "indirect"
      },
      "to": {
        "lastModified": 1779336838,
        "narHash": "sha256-n1+l78hJRABp4cQHKeD0BVByT0vZLPqd09Tvoq8Q+d8=",
        "owner": "nix-community",
        "repo": "home-manager",
        "rev": "928d72376949e222ea4f07b44828a55b0136422e",
        "type": "github"
      }
    },
    {
      "from": {
        "id": "nix-darwin",
        "type": "indirect"
      },
      "to": {
        "lastModified": 1779036909,
        "narHash": "sha256-zXcwYQGCT6pzinK+1dBB2ekTVtfxGZAapb3Evdcu4fY=",
        "owner": "LnL7",
        "repo": "nix-darwin",
        "rev": "56c666e108467d87d13508936aade6d567f2a501",
        "type": "github"
      }
    },
    {
      "from": {
        "id": "nixpkgs",
        "type": "indirect"
      },
      "to": {
        "lastModified": 1779259093,
        "narHash": "sha256-7DKWmH23hL2eYdkxCKeqj2i+yljTKuU+3Nk1UPHOnxc=",
        "owner": "NixOS",
        "repo": "nixpkgs",
        "rev": "d99b013d5d1931ad77fe3912ed218170dec5d9a4",
        "type": "github"
      }
    },
    {
      "from": {
        "id": "ocaml-overlays",
        "type": "indirect"
      },
      "to": {
        "lastModified": 1779058610,
        "narHash": "sha256-UsK0odV9XN6jkuE1b8AND8Ql5XGs8LC1CFNA2Plsz9k=",
        "owner": "nix-ocaml",
        "repo": "nix-overlays",
        "rev": "8e5b42657fa58da0ee069c7e1ce88c22cde1fb0a",
        "type": "github"
      }
    },
    {
      "from": {
        "id": "rust-overlay",
        "type": "indirect"
      },
      "to": {
        "lastModified": 1779333539,
        "narHash": "sha256-lpmN2lrBDZDPjov2cbD3bOOJsI0fkKolKXasYPCqSys=",
        "owner": "oxalica",
        "repo": "rust-overlay",
        "rev": "672fa5fc5608d5cd82286a6f69aaf84a40b4fe41",
        "type": "github"
      }
    },
    {
      "from": {
        "id": "systems",
        "type": "indirect"
      },
      "to": {
        "lastModified": 1681028828,
        "narHash": "sha256-Vy1rq5AaRuLzOxct8nz4T6wlgyUR7zLU309k9mBC768=",
        "owner": "nix-systems",
        "repo": "default",
        "rev": "da67096a3b9bf56a91d16901293e51ba5b49a27e",
        "type": "github"
      }
    },
    {
      "from": {
        "id": "tsgo-effect",
        "type": "indirect"
      },
      "to": {
        "lastModified": 1779378985,
        "narHash": "sha256-mWV4IofxLxOyKCYGJf2DDxqHjcNQR5jYCKUTb1zXYEg=",
        "owner": "Effect-TS",
        "repo": "tsgo",
        "rev": "c84d7f1e69187f4c8784c26fb754882f7acd3b2d",
        "type": "github"
      }
    },
    {
      "from": {
        "id": "unstable",
        "type": "indirect"
      },
      "to": {
        "lastModified": 1778869304,
        "narHash": "sha256-30sZNZoA1cqF5JNO9fVX+wgiQYjB7HJqqJ4ztCDeBZE=",
        "owner": "NixOS",
        "repo": "nixpkgs",
        "rev": "d233902339c02a9c334e7e593de68855ad26c4cb",
        "type": "github"
      }
    }
  ],
  "version": 2
}
